chord_chart-0.3.0.dist-info/METADATA
chord_chart-0.3.0.dist-info/WHEEL
chord_chart/py.typed
chord_chart/_chord_chart.pyi
chord_chart/__init__.py
chord_chart/_chord_chart.cpython-37m-x86_64-linux-gnu.so
chord_chart-0.3.0.dist-info/RECORD
